fusion_tools/__init__.py
fusion_tools/components/__init__.py
fusion_tools/components/annotation.py
fusion_tools/components/base.py
fusion_tools/components/custom.py
fusion_tools/components/external.py
fusion_tools/components/extractors.py
fusion_tools/components/maps.py
fusion_tools/components/overlays.py
fusion_tools/components/plotters.py
fusion_tools/database/__init__.py
fusion_tools/database/api.py
fusion_tools/database/database.py
fusion_tools/database/models.py
fusion_tools/dataset.py
fusion_tools/feature_extraction.py
fusion_tools/fusion/__init__.py
fusion_tools/fusion/data_types.py
fusion_tools/fusion/surveys.py
fusion_tools/fusion/vis.py
fusion_tools/fusion/welcome.py
fusion_tools/handler/__init__.py
fusion_tools/handler/dataset_builder.py
fusion_tools/handler/dataset_uploader.py
fusion_tools/handler/dsa_handler.py
fusion_tools/handler/login.py
fusion_tools/handler/plugin.py
fusion_tools/handler/resource_selector.py
fusion_tools/handler/save_session.py
fusion_tools/handler/survey.py
fusion_tools/simple_fusion.py
fusion_tools/tileserver.py
fusion_tools/utils/__init__.py
fusion_tools/utils/images.py
fusion_tools/utils/omics.py
fusion_tools/utils/shapes.py
fusion_tools/utils/stats.py
fusion_tools/visualization/__init__.py
fusion_tools/visualization/components.py
fusion_tools/visualization/vis_utils.py
fusion_tools-3.6.81.dist-info/LICENSE
fusion_tools-3.6.81.dist-info/METADATA
fusion_tools-3.6.81.dist-info/WHEEL
fusion_tools-3.6.81.dist-info/RECORD
