Metadata-Version: 2.3
Name: fusion-tools
Version: 3.6.81
Summary: Modular visualization and analysis dashboard creation for high-resolution microscopy images.
License: Apache Software License
Author: Sam Border
Author-email: sam.border2256@gmail.com
Requires-Python: >=3.11
Classifier: License :: Other/Proprietary License
Classifier: Programming Language :: Python :: 3
Classifier: Programming Language :: Python :: 3.11
Classifier: Programming Language :: Python :: 3.12
Classifier: Programming Language :: Python :: 3.13
Requires-Dist: bcrypt (>=5.0.0,<6.0.0)
Requires-Dist: dash (>=3.2.0,<4.0.0)
Requires-Dist: dash-bootstrap-components (>=2.0.4,<3.0.0)
Requires-Dist: dash-leaflet (>=1.1.3,<2.0.0)
Requires-Dist: dash-mantine-components (>=2.3.0,<3.0.0)
Requires-Dist: dash-uploader (>=0.6.1,<0.7.0)
Requires-Dist: fastapi (>=0.119.0,<0.120.0)
Requires-Dist: geojson (>=3.2.0,<4.0.0)
Requires-Dist: geopandas (>=1.1.1,<2.0.0)
Requires-Dist: girder-client (>=3.2.11,<4.0.0)
Requires-Dist: girder-job-sequence (>=0.2.7,<0.3.0)
Requires-Dist: large-image[openjpeg,openslide,tifffile] (>=1.33.3,<2.0.0)
Requires-Dist: pandas (>=2.3.3,<3.0.0)
Requires-Dist: rasterio (>=1.4.3,<2.0.0)
Requires-Dist: scikit-image (>=0.25.2,<0.26.0)
Requires-Dist: shapely (>=2.1.2,<3.0.0)
Requires-Dist: sqlalchemy (>=2.0.44,<3.0.0)
Requires-Dist: statsmodels (>=0.14.5,<0.15.0)
Requires-Dist: tqdm (>=4.67.1,<5.0.0)
Requires-Dist: umap-learn (>=0.5.9.post2,<0.6.0)
Requires-Dist: uvicorn (>=0.37.0,<0.38.0)
